fsm_seq_det/fsm_1010_tggle.v
module fsm_1010_tggle(
input clk,rst,
input seq,
output wire out
);

parameter S0 = 4'b0000;
parameter S1 = 4'b0001;
parameter S2 = 4'b0010;
parameter S3 = 4'b0011;
parameter S4 = 4'b0100;
parameter S5 = 4'b0101;
parameter S6 = 4'b0110;
parameter S7 = 4'b0111;
parameter S8 = 4'b1000;

          reg [3:0]state,next_state;

always@(posedge clk or posedge rst)
        if(rst)
           state <= S0;
        else 
           state <= next_state;

always@(*)
begin
    next_state = S0;
    case(state)
 S0:if(seq)
  next_state <= S1;
 else 
  next_state <= S0;

 S1:if(seq)
  next_state <= S1;
 else 
  next_state <= S2;

 S2:if(seq)
  next_state <= S3;
 else 
  next_state <= S0;

 S3:if(seq)
  next_state <= S1;
 else 
  next_state <= S4;

 S4:if(seq)
  next_state <= S5;
 else 
  next_state <= S6;

 S5:if(seq)
  next_state <= S7;
 else 
  next_state <= S2;

 S6:if(seq)
  next_state <= S7;
 else 
  next_state <= S6;

 S7:if(seq)
  next_state <= S7;
 else 
  next_state <= S8;

 S8:if(seq)
  next_state <= S5;
 else 
  next_state <= S6;

endcase 
end 

assign out =((state == S4) ||(state == S5) 
||(state == S6) ||(state == S7) || (state == S8));

endmodule

fsm_seq_det/fsm_1010_tggle_tb.v
module fsm_1010_tggle_tb();
reg clk,rst;
reg seq;
wire out;

fsm_1010_tggle DUT(clk,rst,seq,out);

reg [2*8:1] string_state;   //To print state
integer j;

always@(*)
case(DUT.state) 
          4'b0000: string_state = "S0";
          4'b0001: string_state = "S1";
          4'b0010: string_state = "S2";
          4'b0011: string_state = "S3";
          4'b0100: string_state = "S4";
          4'b0101: string_state = "S5";
          4'b0110: string_state = "S6";
          4'b0111: string_state = "S7";
          4'b1000: string_state = "S8";
endcase 

initial clk=0;
always #10 clk =~ clk;

task reset;
begin
    @(negedge clk)
     rst = 1'b1;
    @(negedge clk)
     rst = 1'b0; 
end 
endtask 

task stimulus;
input i;
begin
    @(negedge clk)
     seq = i; 
end 
endtask 

initial 
begin
  reset();
  for(j=0;j<10;j=j+1)
  begin
    stimulus(1'b0);
    stimulus(1'b1); 
  end 
  stimulus(1'b0);
  stimulus(1'b0);
  stimulus(1'b1);
  stimulus(1'b0);
  stimulus(1'b1);
  stimulus(1'b0);
  stimulus(1'b0);
  stimulus(1'b1);
  stimulus(1'b0);
  stimulus(1'b0);
  reset();
  stimulus(1'b0);
  stimulus(1'b1);
  stimulus(1'b0);
  stimulus(1'b1);
  stimulus(1'b0);
  stimulus(1'b0);
  stimulus(1'b1);
  stimulus(1'b0);
#500;
$finish;
end 
initial 
begin
    $dumpfile("naveen.vcd");
    $dumpvars(0,fsm_1010_tggle_tb); 
end 
endmodule

fsm_seq_det/naveen.vcd
$date
	Tue Jul 07 12:05:12 2026
$end
$version
	Icarus Verilog
$end
$timescale
	1s
$end
$scope module fsm_1010_tggle_tb $end
$var wire 1 ! out $end
$var reg 1 " clk $end
$var reg 1 # rst $end
$var reg 1 $ seq $end
$var reg 16 % string_state [16:1] $end
$var integer 32 & j [31:0] $end
$scope module DUT $end
$var wire 1 " clk $end
$var wire 1 ! out $end
$var wire 1 # rst $end
$var wire 1 $ seq $end
$var reg 4 ' next_state [3:0] $end
$var reg 4 ( state [3:0] $end
$upscope $end
$scope task reset $end
$upscope $end
$scope task stimulus $end
$var reg 1 ) i $end
$upscope $end
$upscope $end
$enddefinitions $end
#0
$dumpvars
x)
bx (
bx '
bx &
bx %
x$
x#
0"
x!
$end
#10
1"
#20
0!
b0 '
b101001100110000 %
b0 (
1#
0"
#30
1"
#40
0)
b0 &
0#
0"
#50
1"
#60
1)
0$
0"
#70
1"
#80
b1 '
0)
b1 &
1$
0"
#90
b1 '
b101001100110001 %
b1 (
1"
#100
b10 '
1)
0$
0"
#110
b0 '
b101001100110010 %
b10 (
1"
#120
b11 '
0)
b10 &
1$
0"
#130
b1 '
b101001100110011 %
b11 (
1"
#140
b100 '
1)
0$
0"
#150
1!
b110 '
b101001100110100 %
b100 (
1"
#160
b101 '
0)
b11 &
1$
0"
#170
b111 '
b101001100110101 %
b101 (
1"
#180
b10 '
1)
0$
0"
#190
0!
b0 '
b101001100110010 %
b10 (
1"
#200
b11 '
0)
b100 &
1$
0"
#210
b1 '
b101001100110011 %
b11 (
1"
#220
b100 '
1)
0$
0"
#230
1!
b110 '
b101001100110100 %
b100 (
1"
#240
b101 '
0)
b101 &
1$
0"
#250
b111 '
b101001100110101 %
b101 (
1"
#260
b10 '
1)
0$
0"
#270
0!
b0 '
b101001100110010 %
b10 (
1"
#280
b11 '
0)
b110 &
1$
0"
#290
b1 '
b101001100110011 %
b11 (
1"
#300
b100 '
1)
0$
0"
#310
1!
b110 '
b101001100110100 %
b100 (
1"
#320
b101 '
0)
b111 &
1$
0"
#330
b111 '
b101001100110101 %
b101 (
1"
#340
b10 '
1)
0$
0"
#350
0!
b0 '
b101001100110010 %
b10 (
1"
#360
b11 '
0)
b1000 &
1$
0"
#370
b1 '
b101001100110011 %
b11 (
1"
#380
b100 '
1)
0$
0"
#390
1!
b110 '
b101001100110100 %
b100 (
1"
#400
b101 '
0)
b1001 &
1$
0"
#410
b111 '
b101001100110101 %
b101 (
1"
#420
b10 '
1)
0$
0"
#430
0!
b0 '
b101001100110010 %
b10 (
1"
#440
b11 '
0)
b1010 &
1$
0"
#450
b1 '
b101001100110011 %
b11 (
1"
#460
b100 '
0$
0"
#470
1!
b110 '
b101001100110100 %
b100 (
1"
#480
1)
0"
#490
b110 '
b101001100110110 %
b110 (
1"
#500
b111 '
0)
1$
0"
#510
b111 '
b101001100110111 %
b111 (
1"
#520
b1000 '
1)
0$
0"
#530
b110 '
b101001100111000 %
b1000 (
1"
#540
b101 '
0)
1$
0"
#550
b111 '
1!
b101001100110101 %
b101 (
1"
#560
b10 '
0$
0"
#570
0!
b0 '
b101001100110010 %
b10 (
1"
#580
1)
0"
#590
b101001100110000 %
b0 (
1"
#600
b1 '
0)
1$
0"
#610
b1 '
b101001100110001 %
b1 (
1"
#620
b10 '
0$
0"
#630
b0 '
b101001100110010 %
b10 (
1"
#640
0"
#650
b101001100110000 %
b0 (
1"
#660
1#
0"
#670
1"
#680
0#
0"
#690
1"
#700
1)
0"
#710
1"
#720
b1 '
0)
1$
0"
#730
b1 '
b101001100110001 %
b1 (
1"
#740
b10 '
1)
0$
0"
#750
b0 '
b101001100110010 %
b10 (
1"
#760
b11 '
0)
1$
0"
#770
b1 '
b101001100110011 %
b11 (
1"
#780
b100 '
0$
0"
#790
1!
b110 '
b101001100110100 %
b100 (
1"
#800
1)
0"
#810
b110 '
b101001100110110 %
b110 (
1"
#820
b111 '
0)
1$
0"
#830
b111 '
b101001100110111 %
b111 (
1"
#840
b1000 '
0$
0"
#850
b110 '
b101001100111000 %
b1000 (
1"
#860
0"
#870
b110 '
1!
b101001100110110 %
b110 (
1"
