fsm_seq_det/fsm_1010_tggle.v
module fsm_1010_tggle(
input clk,rst,
input seq,
output wire out
);

parameter S0 = 4'b0000;
parameter S1 = 4'b0001;
parameter S2 = 4'b0010;
parameter S3 = 4'b0011;
parameter S4 = 4'b0100;
parameter S5 = 4'b0101;
parameter S6 = 4'b0110;
parameter S7 = 4'b0111;
parameter S8 = 4'b1000;

          reg [3:0]state,next_state;

always@(posedge clk or posedge rst)
        if(rst)
           state <= S0;
        else 
           state <= next_state;

always@(*)
begin
    next_state = S0;
    case(state)
 S0:if(seq)
  next_state <= S1;
 else 
  next_state <= S0;

 S1:if(seq)
  next_state <= S1;
 else 
  next_state <= S2;

 S2:if(seq)
  next_state <= S3;
 else 
  next_state <= S0;

 S3:if(seq)
  next_state <= S1;
 else 
  next_state <= S4;

 S4:if(seq)
  next_state <= S5;
 else 
  next_state <= S6;

 S5:if(seq)
  next_state <= S7;
 else 
  next_state <= S2;

 S6:if(seq)
  next_state <= S7;
 else 
  next_state <= S6;

 S7:if(seq)
  next_state <= S7;
 else 
  next_state <= S8;

 S8:if(seq)
  next_state <= S5;
 else 
  next_state <= S6;

endcase 
end 

assign out =((state == S4) ||(state == S5) 
||(state == S6) ||(state == S7) || (state == S8));

endmodule

fsm_seq_det/fsm_1010_tggle_tb.v
module fsm_1010_tggle_tb();
reg clk,rst;
reg seq;
wire out;

fsm_1010_tggle DUT(clk,rst,seq,out);

reg [2*8:1] string_state;   //To print state
integer j;

always@(*)
case(DUT.state) 
          4'b0000: string_state = "S0";
          4'b0001: string_state = "S1";
          4'b0010: string_state = "S2";
          4'b0011: string_state = "S3";
          4'b0100: string_state = "S4";
          4'b0101: string_state = "S5";
          4'b0110: string_state = "S6";
          4'b0111: string_state = "S7";
          4'b1000: string_state = "S8";
endcase 

initial clk=0;
always #10 clk =~ clk;

task reset;
begin
    @(negedge clk)
     rst = 1'b1;
    @(negedge clk)
     rst = 1'b0; 
end 
endtask 

task stimulus;
input i;
begin
    @(negedge clk)
     seq = i; 
end 
endtask 

initial 
begin
  reset();
  for(j=0;j<10;j=j+1)
  begin
    stimulus(1'b0);
    stimulus(1'b1); 
  end 
  stimulus(1'b0);
  stimulus(1'b0);
  stimulus(1'b1);
  stimulus(1'b0);
  stimulus(1'b1);
  stimulus(1'b0);
  stimulus(1'b0);
  stimulus(1'b1);
  stimulus(1'b0);
  stimulus(1'b0);
  reset();
  stimulus(1'b0);
  stimulus(1'b1);
  stimulus(1'b0);
  stimulus(1'b1);
  stimulus(1'b0);
  stimulus(1'b0);
  stimulus(1'b1);
  stimulus(1'b0);
#500;
$finish;
end 
initial 
begin
    $dumpfile("naveen.vcd");
    $dumpvars(0,fsm_1010_tggle_tb); 
end 
endmodule

fsm_seq_det/simulation/simulation/modelsim/naveen.vcd
$date
	Tue Jul 07 11:16:20 2026
$end
$version
	ModelSim Version 10.5b
$end
$timescale
	1ps
$end

$scope module fsm_1010_tggle_tb $end
$var reg 1 ! clk $end
$var reg 1 " rst $end
$var reg 1 # seq $end
$var wire 1 $ out $end
$var reg 16 % string_state [16:1] $end
$var integer 32 & j $end

$scope task reset $end
$upscope $end

$scope task stimulus $end
$var reg 1 ' i $end
$upscope $end

$scope module DUT $end
$var parameter 4 ( S0 $end
$var parameter 4 ) S1 $end
$var parameter 4 * S2 $end
$var parameter 4 + S3 $end
$var parameter 4 , S4 $end
$var parameter 4 - S5 $end
$var parameter 4 . S6 $end
$var parameter 4 / S7 $end
$var parameter 4 0 S8 $end
$var wire 1 1 clk $end
$var wire 1 2 rst $end
$var wire 1 3 seq $end
$var wire 1 $ out $end
$var reg 4 4 state [3:0] $end
$var reg 4 5 next_state [3:0] $end
$upscope $end
$upscope $end
$enddefinitions $end
#0
$dumpvars
0!
x"
x#
bx 4
bx 5
bx %
x'
b0 (
b1 )
b10 *
b11 +
b100 ,
b101 -
b110 .
b111 /
b1000 0
bx &
x$
x3
x2
01
$end
#10
1!
11
#20
0!
01
1"
12
b0 4
0$
b101001100110000 %
b0 5
#30
1!
11
#40
0!
01
0"
b0 &
0'
02
#50
1!
11
#60
0!
01
0#
1'
03
#70
1!
11
#80
0!
01
1#
b1 &
0'
13
b1 5
#90
1!
11
b1 4
b101001100110001 %
b0 5
b1 5
#100
0!
01
0#
1'
03
b0 5
b10 5
#110
1!
11
b10 4
b101001100110010 %
b0 5
#120
0!
01
1#
b10 &
0'
13
b11 5
#130
1!
11
b11 4
b101001100110011 %
b0 5
b1 5
#140
0!
01
0#
1'
03
b0 5
b100 5
#150
1!
11
b100 4
1$
b101001100110100 %
b0 5
b110 5
#160
0!
01
1#
b11 &
0'
13
b0 5
b101 5
#170
1!
11
b101 4
b101001100110101 %
b0 5
b111 5
#180
0!
01
0#
1'
03
b0 5
b10 5
#190
1!
11
b10 4
0$
b101001100110010 %
b0 5
#200
0!
01
1#
b100 &
0'
13
b11 5
#210
1!
11
b11 4
b101001100110011 %
b0 5
b1 5
#220
0!
01
0#
1'
03
b0 5
b100 5
#230
1!
11
b100 4
1$
b101001100110100 %
b0 5
b110 5
#240
0!
01
1#
b101 &
0'
13
b0 5
b101 5
#250
1!
11
b101 4
b101001100110101 %
b0 5
b111 5
#260
0!
01
0#
1'
03
b0 5
b10 5
#270
1!
11
b10 4
0$
b101001100110010 %
b0 5
#280
0!
01
1#
b110 &
0'
13
b11 5
#290
1!
11
b11 4
b101001100110011 %
b0 5
b1 5
#300
0!
01
0#
1'
03
b0 5
b100 5
#310
1!
11
b100 4
1$
b101001100110100 %
b0 5
b110 5
#320
0!
01
1#
b111 &
0'
13
b0 5
b101 5
#330
1!
11
b101 4
b101001100110101 %
b0 5
b111 5
#340
0!
01
0#
1'
03
b0 5
b10 5
#350
1!
11
b10 4
0$
b101001100110010 %
b0 5
#360
0!
01
1#
b1000 &
0'
13
b11 5
#370
1!
11
b11 4
b101001100110011 %
b0 5
b1 5
#380
0!
01
0#
1'
03
b0 5
b100 5
#390
1!
11
b100 4
1$
b101001100110100 %
b0 5
b110 5
#400
0!
01
1#
b1001 &
0'
13
b0 5
b101 5
#410
1!
11
b101 4
b101001100110101 %
b0 5
b111 5
#420
0!
01
0#
1'
03
b0 5
b10 5
#430
1!
11
b10 4
0$
b101001100110010 %
b0 5
#440
0!
01
1#
b1010 &
0'
13
b11 5
#450
1!
11
b11 4
b101001100110011 %
b0 5
b1 5
#460
0!
01
0#
03
b0 5
b100 5
#470
1!
11
b100 4
1$
b101001100110100 %
b0 5
b110 5
#480
0!
01
1'
#490
1!
11
b110 4
b101001100110110 %
b0 5
b110 5
#500
0!
01
1#
0'
13
b0 5
b111 5
#510
1!
11
b111 4
b101001100110111 %
b0 5
b111 5
#520
0!
01
0#
1'
03
b0 5
b1000 5
#530
1!
11
b1000 4
b101001100111000 %
b0 5
b110 5
#540
0!
01
1#
0'
13
b0 5
b101 5
#550
1!
11
b101 4
b101001100110101 %
b0 5
b111 5
#560
0!
01
0#
03
b0 5
b10 5
#570
1!
11
b10 4
0$
b101001100110010 %
b0 5
#580
0!
01
1'
#590
1!
11
b0 4
b101001100110000 %
#600
0!
01
1#
0'
13
b1 5
#610
1!
11
b1 4
b101001100110001 %
b0 5
b1 5
#620
0!
01
0#
03
b0 5
b10 5
#630
1!
11
b10 4
b101001100110010 %
b0 5
#640
0!
01
#650
1!
11
b0 4
b101001100110000 %
#660
0!
01
1"
12
#670
1!
11
#680
0!
01
0"
02
#690
1!
11
#700
0!
01
1'
#710
1!
11
#720
0!
01
1#
0'
13
b1 5
#730
1!
11
b1 4
b101001100110001 %
b0 5
b1 5
#740
0!
01
0#
1'
03
b0 5
b10 5
#750
1!
11
b10 4
b101001100110010 %
b0 5
#760
0!
01
1#
0'
13
b11 5
#770
1!
11
b11 4
b101001100110011 %
b0 5
b1 5
#780
0!
01
0#
03
b0 5
b100 5
#790
1!
11
b100 4
1$
b101001100110100 %
b0 5
b110 5
#800
0!
01
1'
#810
1!
11
b110 4
b101001100110110 %
b0 5
b110 5
#820
0!
01
1#
0'
13
b0 5
b111 5
#830
1!
11
b111 4
b101001100110111 %
b0 5
b111 5
#840
0!
01
0#
03
b0 5
b1000 5
#850
1!
11
b1000 4
b101001100111000 %
b0 5
b110 5
#860
0!
01
#870
1!
11
b110 4
b101001100110110 %
b0 5
b110 5
